tcsctl/__init__.py
tcsctl/blueprint.py
tcsctl/client.py
tcsctl/common.py
tcsctl/deployment.py
tcsctl/enums.py
tcsctl/environment.py
tcsctl/exceptions.py
tcsctl/main.py
tcsctl/models.py
tcsctl/project.py
tcsctl/template.py
tcsctl/schemas/__init__.py
tcsctl/schemas/schema.blueprint.yaml
tcsctl/schemas/schema.config.yaml
tcsctl/schemas/schema.environment.yaml
tcsctl/schemas/schema.template.yaml
tcsctl-0.2.0.dist-info/AUTHORS
tcsctl-0.2.0.dist-info/LICENSE
tcsctl-0.2.0.dist-info/METADATA
tcsctl-0.2.0.dist-info/WHEEL
tcsctl-0.2.0.dist-info/entry_points.txt
tcsctl-0.2.0.dist-info/pbr.json
tcsctl-0.2.0.dist-info/top_level.txt
tcsctl-0.2.0.dist-info/RECORD
