Metadata-Version: 2.1
Name: tcsctl
Version: 0.2.0
Summary: CLI for The Cloudsphere
Home-page: https://github.com/thecloudsphere/tcsctl
Author: OSISM GmbH
Author-email: info@osism.tech
Classifier: Development Status :: 3 - Alpha
Classifier: Environment :: Console
Classifier: Intended Audience :: Developers
Classifier: Intended Audience :: Information Technology
Classifier: License :: OSI Approved :: Apache Software License
Classifier: Operating System :: OS Independent
Classifier: Programming Language :: Python
Classifier: Programming Language :: Python :: 3 :: Only
Classifier: Programming Language :: Python :: 3
Classifier: Programming Language :: Python :: 3.8
Classifier: Programming Language :: Python :: 3.9
Classifier: Programming Language :: Python :: 3.10
Requires-Python: >=3.8
License-File: LICENSE
License-File: AUTHORS
Requires-Dist: appdirs (==1.4.4)
Requires-Dist: certifi (==2022.12.7)
Requires-Dist: charset-normalizer (==3.1.0)
Requires-Dist: click (==8.1.3)
Requires-Dist: colorama (==0.4.6)
Requires-Dist: dynaconf (==3.1.12)
Requires-Dist: idna (==3.4)
Requires-Dist: Jinja2 (==3.1.2)
Requires-Dist: loguru (==0.7.0)
Requires-Dist: markdown-it-py (==2.2.0)
Requires-Dist: MarkupSafe (==2.1.2)
Requires-Dist: mdurl (==0.1.2)
Requires-Dist: numpy (==1.24.3)
Requires-Dist: pandas (==2.0.1)
Requires-Dist: pbr (==5.11.1)
Requires-Dist: pydantic (==1.10.7)
Requires-Dist: Pygments (==2.15.1)
Requires-Dist: PyJWT (==2.6.0)
Requires-Dist: python-dateutil (==2.8.2)
Requires-Dist: pytz (==2023.3)
Requires-Dist: PyYAML (==6.0)
Requires-Dist: requests (==2.29.0)
Requires-Dist: rich (==13.3.5)
Requires-Dist: shellingham (==1.5.0.post1)
Requires-Dist: six (==1.16.0)
Requires-Dist: tabulate (==0.9.0)
Requires-Dist: typer (==0.9.0)
Requires-Dist: typing-extensions (==4.5.0)
Requires-Dist: tzdata (==2023.3)
Requires-Dist: urllib3 (==1.26.15)
Requires-Dist: yamale (==4.0.4)
